da4py/__init__.py
da4py/main/__init__.py
da4py/main/analytics/__init__.py
da4py/main/analytics/amstc.py
da4py/main/analytics/antiAlignmentBetweenNets.py
da4py/main/conformanceChecking/__init__.py
da4py/main/conformanceChecking/antiAlignmentBetweenNets.py
da4py/main/conformanceChecking/conformanceArtefacts.py
da4py/main/conformanceChecking/distancesToFormulas.py
da4py/main/objects/__init__.py
da4py/main/objects/logToFormulas.py
da4py/main/objects/logToPn.py
da4py/main/objects/pnToFormulas.py
da4py/main/utils/__init__.py
da4py/main/utils/formulas.py
da4py/main/utils/unSat2qbfReader.py
da4py/main/utils/variablesGenerator.py
da4py/tests/__init__.py
da4py/tests/test_amstc.py
da4py/tests/test_conformanceArtefacts.py
da4py/tests/test_treeRepair.py
da4py/tests/test_variablesGenerator.py
da4py-0.0.8.dist-info/LICENSE
da4py-0.0.8.dist-info/METADATA
da4py-0.0.8.dist-info/WHEEL
da4py-0.0.8.dist-info/top_level.txt
da4py-0.0.8.dist-info/RECORD
