Metadata-Version: 2.1
Name: da4py
Version: 0.0.8
Summary: da4py implements state-of-the-art Process Mining methods over SAT encoding. An Ocaml version is Darksider.
Home-page: https://github.com/BoltMaud/da4py
Author: Boltenhagen Mathilde
Author-email: boltenhagen@lsv.fr
License: UNKNOWN
Platform: UNKNOWN
Classifier: Programming Language :: Python :: 3
Classifier: License :: OSI Approved :: MIT License
Classifier: Operating System :: OS Independent
Requires-Python: >=3.6
